src/__init__.py
src/module.py
paketapipi-0.1.dist-info/METADATA
paketapipi-0.1.dist-info/WHEEL
paketapipi-0.1.dist-info/top_level.txt
paketapipi-0.1.dist-info/RECORD
