Metadata-Version: 2.4
Name: paketapipi
Version: 0.1
Summary: Описание пакета
Home-page: https://github.com/твой-профиль/my_package
Author: Твое Имя
Author-email: you@example.com
Classifier: Programming Language :: Python :: 3
Dynamic: author
Dynamic: author-email
Dynamic: classifier
Dynamic: description
Dynamic: description-content-type
Dynamic: home-page
Dynamic: summary
